rekcurd_dashboard/__init__.py
rekcurd_dashboard/_project.py
rekcurd_dashboard/_version.py
rekcurd_dashboard/apis/__init__.py
rekcurd_dashboard/apis/api_admin.py
rekcurd_dashboard/apis/api_application.py
rekcurd_dashboard/apis/api_data_server.py
rekcurd_dashboard/apis/api_evaluation.py
rekcurd_dashboard/apis/api_kubernetes.py
rekcurd_dashboard/apis/api_kubernetes_secret.py
rekcurd_dashboard/apis/api_misc.py
rekcurd_dashboard/apis/api_model.py
rekcurd_dashboard/apis/api_project.py
rekcurd_dashboard/apis/api_service.py
rekcurd_dashboard/apis/api_service_deployment.py
rekcurd_dashboard/apis/api_service_routing.py
rekcurd_dashboard/apis/common.py
rekcurd_dashboard/apis/kubernetes_handler.py
rekcurd_dashboard/auth/__init__.py
rekcurd_dashboard/auth/authenticator.py
rekcurd_dashboard/auth/ldap.py
rekcurd_dashboard/console_scripts/__init__.py
rekcurd_dashboard/console_scripts/db_handler.py
rekcurd_dashboard/console_scripts/errors.py
rekcurd_dashboard/console_scripts/server_handler.py
rekcurd_dashboard/console_scripts/template_handler.py
rekcurd_dashboard/core/__init__.py
rekcurd_dashboard/core/create_app.py
rekcurd_dashboard/core/rekcurd_dashboard_client.py
rekcurd_dashboard/data_servers/__init__.py
rekcurd_dashboard/data_servers/aws_s3_handler.py
rekcurd_dashboard/data_servers/ceph_handler.py
rekcurd_dashboard/data_servers/data_handler.py
rekcurd_dashboard/data_servers/gcs_handler.py
rekcurd_dashboard/data_servers/local_handler.py
rekcurd_dashboard/logger/__init__.py
rekcurd_dashboard/logger/logger_fluent.py
rekcurd_dashboard/logger/logger_interface.py
rekcurd_dashboard/logger/logger_jsonlogger.py
rekcurd_dashboard/models/__init__.py
rekcurd_dashboard/models/application.py
rekcurd_dashboard/models/application_user_role.py
rekcurd_dashboard/models/dao.py
rekcurd_dashboard/models/data_server.py
rekcurd_dashboard/models/evaluation.py
rekcurd_dashboard/models/evaluation_result.py
rekcurd_dashboard/models/kubernetes.py
rekcurd_dashboard/models/model.py
rekcurd_dashboard-1.0.1.post6.dist-info/LICENSE
rekcurd_dashboard-1.0.1.post6.dist-info/METADATA
rekcurd_dashboard-1.0.1.post6.dist-info/WHEEL
rekcurd_dashboard-1.0.1.post6.dist-info/entry_points.txt
rekcurd_dashboard-1.0.1.post6.dist-info/top_level.txt
rekcurd_dashboard-1.0.1.post6.dist-info/RECORD
